foundry_tree/__init__.py
foundry_tree/tree.py
openfoundry-tree/__init__.py
openfoundry-tree/tree.py
openfoundry_tree/__init__.py
openfoundry_tree/tree.py
openfoundry_tree-0.2.0.dist-info/METADATA
openfoundry_tree-0.2.0.dist-info/RECORD
openfoundry_tree-0.2.0.dist-info/WHEEL
openfoundry_tree-0.2.0.dist-info/top_level.txt
