Metadata-Version: 2.1
Name: openfoundry-tree
Version: 0.2.0
Summary: OpenFoundry's Tree object code.
Home-page: https://gitlab.com/koeng/openfoundry-tree
Author: Keoni Gandall
Author-email: koeng101@gmail.com
License: UNKNOWN
Platform: UNKNOWN
Classifier: Programming Language :: Python :: 3
Classifier: License :: OSI Approved :: MIT License
Classifier: Operating System :: OS Independent
